<Spele Laiks="2014/12/06" Vieta="Stadions Daugava" Skatitaji="9472">
    <VT Vards="George" Uzvards="Freeman"/>
    <T Vards="Tom" Uzvards="Newbie"/>
    <T Vards="Maris" Uzvards="Onka"/>
    <Komanda Nosaukums="ABC">
        <Speletaji>
            <Speletajs Nr="1" Vards="Maksim" Uzvards="Selivonchik" Loma="V"/>
            <Speletajs Nr="3" Vards="Vadim" Uzvards="Naumec" Loma="U"/>
            <Speletajs Nr="4" Vards="Igor" Uzvards="Melnichuk" Loma="U"/>
            <Speletajs Nr="5" Vards="Manuel" Uzvards="Nordzhera" Loma="A"/>
            <Speletajs Nr="6" Vards="Branislav" Uzvards="Ivanovich" Loma="A"/>
            <Speletajs Nr="7" Vards="Ivan" Uzvards="Nosikov" Loma="U"/>
            <Speletajs Nr="8" Vards="Vladimir" Uzvards="Afanasjev" Loma="A"/>
            <Speletajs Nr="9" Vards="Andris" Uzvards="Micitis" Loma="U"/>
            <Speletajs Nr="10" Vards="Andrej" Uzvards="Lebedev" Loma="A"/>
            <Speletajs Nr="11" Vards="Vitalij" Uzvards="Parmalis" Loma="A"/>
            <Speletajs Nr="12" Vards="Maksim" Uzvards="Parmalis" Loma="A"/>
            <Speletajs Nr="13" Vards="Andrej" Uzvards="Grishaev" Loma="U"/>
            <Speletajs Nr="14" Vards="Andrej" Uzvards="Miller" Loma="U"/>
            <Speletajs Nr="15" Vards="Artur" Uzvards="Maksimov" Loma="A"/>
        </Speletaji>
        <Pamatsastavs>
            <Speletajs Nr="1"/>
            <Speletajs Nr="3"/>
            <Speletajs Nr="6"/>
            <Speletajs Nr="7"/>
            <Speletajs Nr="8"/>
            <Speletajs Nr="9"/>
            <Speletajs Nr="10"/>
            <Speletajs Nr="12"/>
            <Speletajs Nr="13"/>
            <Speletajs Nr="14"/>
            <Speletajs Nr="15"/>
        </Pamatsastavs>
        <Varti>
            <VG Laiks="44:32" Nr="7" Sitiens="N">
                <P Nr="3"/>
            </VG>
        </Varti>
        <Mainas>
            <Maina Laiks="53:58" Nr1="6" Nr2="11"/>
        </Mainas>
    </Komanda>
    <Komanda Nosaukums="XYZ">
        <Speletaji>
            <Speletajs Nr="8" Vards="Jake" Uzvards="Delhomme" Loma="A"/>
            <Speletajs Nr="9" Vards="Matt" Uzvards="Moore" Loma="U"/>
            <Speletajs Nr="10" Vards="Josh" Uzvards="McCown" Loma="V"/>
            <Speletajs Nr="12" Vards="Angelo" Uzvards="Williams" Loma="A"/>
            <Speletajs Nr="14" Vards="Jonathan" Uzvards="Stewart" Loma="A"/>
            <Speletajs Nr="21" Vards="Branislav" Uzvards="Ivanovich" Loma="A"/>
            <Speletajs Nr="24" Vards="Jarett" Uzvards="Dillard" Loma="U"/>
            <Speletajs Nr="26" Vards="Jerome" Uzvards="Felton" Loma="A"/>
            <Speletajs Nr="33" Vards="Jarett" Uzvards="Dillard" Loma="U"/>
            <Speletajs Nr="44" Vards="Mike" Uzvards="Senderos" Loma="A"/>
            <Speletajs Nr="45" Vards="Vito" Uzvards="Mannone" Loma="A"/>
            <Speletajs Nr="47" Vards="Tyrell" Uzvards="Sutton" Loma="A"/>
            <Speletajs Nr="49" Vards="Mike" Uzvards="Goodson" Loma="V"/>
            <Speletajs Nr="51" Vards="Steve" Uzvards="Smith" Loma="U"/>
            <Speletajs Nr="58" Vards="Muhsin" Uzvards="Muhammad" Loma="A"/>
            <Speletajs Nr="63" Vards="Kenny" Uzvards="Moore" Loma="U"/>
        </Speletaji>
        <Pamatsastavs>
            <Speletajs Nr="8"/>
            <Speletajs Nr="9"/>
            <Speletajs Nr="12"/>
            <Speletajs Nr="14"/>
            <Speletajs Nr="21"/>
            <Speletajs Nr="24"/>
            <Speletajs Nr="26"/>
            <Speletajs Nr="44"/>
            <Speletajs Nr="45"/>
            <Speletajs Nr="47"/>
            <Speletajs Nr="49"/>
        </Pamatsastavs>
        <Varti>
            <VG Laiks="42:00" Nr="9" Sitiens="J"></VG>
            <VG Laiks="55:00" Nr="63" Sitiens="J"></VG>
        </Varti>
        <Sodi>
            <Sods Laiks="78:11" Nr="49"/>
            <Sods Laiks="85:57" Nr="12"/>
        </Sodi>
        <Mainas>
            <Maina Laiks="50:38" Nr1="9" Nr2="63"/>
        </Mainas>
    </Komanda>
</Spele>